majority/or_gate.vhdl
----------------------------------------------------------------------------------
-- Filename : majority.vhdl
-- Author : Antonio Alejandro Andara Lara
-- Date : 25-Oct-10-2022
-- Design Name: or_gate
-- Module Name: majority
-- Project Name: VHDL_essentials
-- Description : In this file go over a simple design for a two input or gate
-- Additional Comments:
-- Copyright : University of Alberta, 2022
-- License : MIT
----------------------------------------------------------------------------------

LIBRARY IEEE;
USE IEEE.STD_LOGIC_1164.ALL;


ENTITY or_gate IS
    PORT (
        or_input : IN STD_LOGIC_VECTOR(1 DOWNTO 0);
        or_out : OUT STD_LOGIC
    );
END or_gate;


ARCHITECTURE Behavioral OF or_gate IS

BEGIN
    PROCESS (or_input) IS BEGIN
        CASE(or_input) IS
            WHEN "00" => or_out <= '0';
            WHEN OTHERS => or_out <= '1';
        END CASE;
    END PROCESS;

END Behavioral;

majority/and_gate.vhdl
----------------------------------------------------------------------------------
-- Filename : majority.vhdl
-- Author : Antonio Alejandro Andara Lara
-- Date : 25-Oct-10-2022
-- Design Name: and_gate
-- Module Name: majority
-- Project Name: VHDL_essentials
-- Description : In this file we make a simple design for a two input and gate
-- Additional Comments:
-- Copyright : University of Alberta, 2022
-- License : MIT
----------------------------------------------------------------------------------


LIBRARY IEEE;
USE IEEE.STD_LOGIC_1164.ALL;


ENTITY and_gate IS
    PORT (
        and_input : IN STD_LOGIC_VECTOR(1 DOWNTO 0);
        and_out : OUT STD_LOGIC
    );
END and_gate;


ARCHITECTURE Behavioral OF and_gate IS
BEGIN
    PROCESS (and_input) BEGIN
        CASE(and_input) IS
            WHEN "11" => and_out <= '1';
            WHEN OTHERS => and_out <= '0';
        END CASE;
    END PROCESS;
END Behavioral;

majority/majority.vhdl
----------------------------------------------------------------------------------
-- Filename : majority.vhdl
-- Author : Antonio Alejandro Andara Lara
-- Date : 25-Oct-10-2022
-- Design Name: majority
-- Module Name: majority
-- Project Name: VHDL_essentials
-- Description : In this file we go over the process of declaring the architecture
-- of a circuit in different ways using VHDL in order to illustrate different
-- approaches and methodologies
-- Additional Comments:
-- Copyright : University of Alberta, 2022
-- License : MIT
----------------------------------------------------------------------------------


-- Importing the standard IEEE libraries
LIBRARY IEEE;
USE IEEE.STD_LOGIC_1164.ALL;


-- Top Module Entity declaration
ENTITY majority IS
    PORT (
        -- 3 bit bus input port
        m_input : IN STD_LOGIC_VECTOR(2 DOWNTO 0);
        -- single bit output
        majority_bit : OUT STD_LOGIC
    );
END majority;


-- The architecture part of a VHDL program describes the internal behavior of the electronic circuit.
-- The architecture describes the underlying functionality of the entity 
-- An architecture is always related to an entity and describes the behavior of said entity
-- An entity can have multiple architectures describing the behavior of the entity


ARCHITECTURE Behavioral OF majority IS
-- declarative part
BEGIN
-- statements part
    PROCESS (m_input)
    BEGIN
    -- we can describe the behavior of our circuit by using a case statement
    -- and following the values of the truth table
        CASE(m_input) IS
            WHEN "000" => majority_bit <= '0';
            WHEN "001" => majority_bit <= '0';
            WHEN "010" => majority_bit <= '0';
            WHEN "011" => majority_bit <= '1';
            WHEN "100" => majority_bit <= '0';
            WHEN "101" => majority_bit <= '1';
            WHEN "110" => majority_bit <= '1';
            WHEN "111" => majority_bit <= '1';
            WHEN OTHERS => majority_bit <= '0';
        END CASE;
    END PROCESS;
END Behavioral;



-- we can clean up our code a little bit by grouping all the states
-- that produce a '0' in the putput into one by using the 'OTHERS'
-- keyword and keeping only the states that produce a '1' in the output
ARCHITECTURE Behavioral1 OF majority IS

BEGIN
    PROCESS (m_input) IS BEGIN
        CASE(m_input) IS
        -- list every case that produces a '1' in the output
            WHEN "011" => majority_bit <= '1';
            WHEN "101" => majority_bit <= '1';
            WHEN "110" => majority_bit <= '1';
            WHEN "111" => majority_bit <= '1';
        -- all other cases will produce an output of '0'
            WHEN OTHERS => majority_bit <= '0';
        END CASE;
    END PROCESS;

END Behavioral1;


-- Another approach is to use an IF statement to simplify our logic
-- let's take a look at one way of doing this
ARCHITECTURE Behavioral2 OF majority IS

BEGIN
    PROCESS (m_input) BEGIN
    -- similar to the case statement we can group all the conditions that produce a '1' in the output
    -- and applying an OR function between all of them
        IF m_input = "011" OR m_input = "101" OR m_input = "110" OR m_input = "111" THEN
            majority_bit <= '1';
        ELSE
            majority_bit <= '0';
        END IF;
    END PROCESS;

END Behavioral2;

-- Using a WITH statement we don't need to create a process
ARCHITECTURE Behavioral3 OF majority IS

BEGIN
    WITH m_input SELECT
        majority_bit <= '1' WHEN "011",
                        '1' WHEN "101",
                        '1' WHEN "110",
                        '1' WHEN "111",
                        '0' WHEN OTHERS;
END Behavioral3;


-- We can also use signals to help us with our logic, in this case
-- we will take the individual inputs and combine them into permutations
-- so they will be easier to handle
ARCHITECTURE Behavioral4 OF majority IS
    -- these signals will represent all possible permutations of any two inputs
    SIGNAL permutation_1 : STD_LOGIC_VECTOR(1 DOWNTO 0);
    SIGNAL permutation_2 : STD_LOGIC_VECTOR(1 DOWNTO 0);
    SIGNAL permutation_3 : STD_LOGIC_VECTOR(1 DOWNTO 0);

BEGIN
    -- here we assign the values of the input to the appropriate signals
    -- permutation_1 gets the two most significant bits
    permutation_1 <= m_input(2 DOWNTO 1);
    -- permutation_2 gets the two least significant bits
    permutation_2 <= m_input(1 DOWNTO 0);
    -- permutation_3 gets the Most Significant Bit and the Least Significant Bit
    -- here we need to use the concatenation opeartor & to turn the individual bits
    -- into a two bit vector
    permutation_3 <= m_input(2) & m_input(0);

    PROCESS (m_input) BEGIN
        -- if any of the permutations is equal to "11" the output gets '1'
        IF permutation_3 = "11" OR permutation_2 = "11" OR permutation_3 = "11" THEN
            majority_bit <= '1';
        ELSE
            majority_bit <= '0';
        END IF;
    END PROCESS;
END Behavioral4;


-- Now we will use a structural approach to write our definition
-- for this we need a pictorial representation of the circuit we
-- want to implement and use that in order to describe both
-- the components and the conections between them. This can
-- come in the form of a gate level diagram or a block diagram
ARCHITECTURE Structural OF majority IS
    -- We need to declare all the intermediate signals of our circuit
    SIGNAL and_1_out, and_2_out, and_3_out, or_1_out, or_2_out : STD_LOGIC := '0';

BEGIN
    -- Here we instantiate the components and the connections between them
    -- a purely Structural architecture doesn't contain any equations or logic in it
    -- only component declarations and the mappings between them.
    and1 : ENTITY work.and_gate(Behavioral) PORT MAP (and_input => m_input(2 DOWNTO 1), and_out => and_1_out);
    and2 : ENTITY work.and_gate(Behavioral) PORT MAP (and_input => m_input(1 DOWNTO 0), and_out => and_2_out);
    and3 : ENTITY work.and_gate(Behavioral) PORT MAP (and_input(0) => m_input(0), and_input(1) => m_input(2), and_out => and_3_out);
    or1 : ENTITY work.or_gate(Behavioral) PORT MAP (or_input(0) => and_1_out, or_input(1) => and_2_out, or_out => or_1_out);
    or2 : ENTITY work.or_gate(Behavioral) PORT MAP (or_input(0) => or_1_out, or_input(1) => and_3_out, or_out => majority_bit);

END Structural;

majority/majority_tb.vhdl
----------------------------------------------------------------------------------
-- Filename : majority_tb.vhdl
-- Author : Antonio Alejandro Andara Lara
-- Date : 25-Oct-10-2022
-- Design Name: majority
-- Module Name: majority_tb
-- Project Name: VHDL_essentials
-- Description : This file is a testbench for a 3 bit majority circuit
-- Additional Comments:
-- Copyright : University of Alberta, 2022
-- License : MIT
----------------------------------------------------------------------------------

LIBRARY IEEE;
USE IEEE.STD_LOGIC_1164.ALL;
USE IEEE.NUMERIC_STD.ALL;

ENTITY majority_tb IS
END majority_tb;

ARCHITECTURE Behavioral OF majority_tb IS

    SIGNAL m_input : STD_LOGIC_VECTOR(2 DOWNTO 0) := "000";
    SIGNAL majority_bit : STD_LOGIC := '0';

BEGIN

    UUT : ENTITY work.majority(Behavioral) PORT MAP(m_input => m_input, majority_bit => majority_bit);

    -- Stimulus proccess to inject all possible input values
    STIMULUS : PROCESS BEGIN
        FOR i IN 0 TO 7 LOOP
            m_input <= STD_LOGIC_VECTOR(TO_UNSIGNED(i, m_input'length));
            WAIT FOR 10 NS;
        END LOOP;
        WAIT;
    END PROCESS;

END Behavioral;

majority/majority.vcd
$date
  Wed Oct 26 09:42:35 2022
$end
$version
  GHDL v0
$end
$timescale
  1 fs
$end
$scope module standard $end
$upscope $end
$scope module std_logic_1164 $end
$upscope $end
$scope module numeric_std $end
$upscope $end
$scope module majority_tb $end
$var reg 3 ! m_input[2:0] $end
$var reg 1 " majority_bit $end
$scope module uut $end
$var reg 3 # m_input[2:0] $end
$var reg 1 $ majority_bit $end
$upscope $end
$upscope $end
$enddefinitions $end
#0
b000 !
0"
b000 #
0$
#10000000
b001 !
b001 #
#20000000
b010 !
b010 #
#30000000
b011 !
1"
b011 #
1$
#40000000
b100 !
0"
b100 #
0$
#50000000
b101 !
1"
b101 #
1$
#60000000
b110 !
b110 #
#70000000
b111 !
b111 #
