monotonic_counter/monotonic_counter.vhdl
----------------------------------------------------------------------------------
-- Filename : monotonic_counter.vhdl
-- Author : Antonio Alejandro Andara Lara
-- Date : 28-Oct-10-2022
-- Design Name: monotonic_counter
-- Module Name: monotonic counter
-- Project Name: VHDL_essentials
-- Description : Example of a monotonic binary counter  with reset
-- Additional Comments:
-- Copyright : University of Alberta, 2022
-- License : CC0 1.0 Universal
----------------------------------------------------------------------------------

LIBRARY IEEE;
USE IEEE.STD_LOGIC_1164.ALL;
USE IEEE.NUMERIC_STD.ALL;

ENTITY monotonic_counter IS
	-- Here we are using the generic as an example for defining the count limit
	GENERIC (STOP_COUNT : NATURAL := 9);
	PORT (
		reset : IN STD_LOGIC;
		clock : IN STD_LOGIC;
		count : OUT STD_LOGIC_VECTOR(31 DOWNTO 0)
	);
END ENTITY monotonic_counter;

ARCHITECTURE Behavioral OF monotonic_counter IS
	-- this signal will hold the value of the counter
	SIGNAL n : NATURAL := 0;

BEGIN
	-- Our signal n is of type natural so we need to change it to std_logic_vector
	-- before assigning its value to count
	count <= STD_LOGIC_VECTOR(to_unsigned(n, count'length));

	PROCESS (clock)
	BEGIN
		IF rising_edge(clock) THEN
			-- counter resets itself when STOP_COUNT value is reached or reset is equal to 1
			IF n = STOP_COUNT OR reset = '1' THEN
				n <= 0;
			ELSE
				n <= n + 1;
			END IF;
		END IF;
	END PROCESS;
END ARCHITECTURE Behavioral;

monotonic_counter/monotonic_counter_tb.vhdl
----------------------------------------------------------------------------------
-- Filename : monotonic_counter_tb.vhdl
-- Author : Antonio Alejandro Andara Lara
-- Date : 28-Oct-10-2022
-- Design Name: monotonic_counter_tb
-- Module Name: monotonic counter
-- Project Name: VHDL_essentials
-- Description : Example of a testbench for a monotonic counter  with reset
-- Additional Comments:
-- Copyright : University of Alberta, 2022
-- License : CC0 1.0 Universal
----------------------------------------------------------------------------------

LIBRARY IEEE;
USE IEEE.STD_LOGIC_1164.ALL;
USE IEEE.NUMERIC_STD.ALL;

ENTITY monotonic_counter_tb IS
	-- empty
END monotonic_counter_tb;

ARCHITECTURE Behavioral OF monotonic_counter_tb IS

	SIGNAL count        : STD_LOGIC_VECTOR(31 DOWNTO 0);
	SIGNAL clock, reset : STD_LOGIC := '0';

BEGIN
	-- Using direct entity instantiation
	UUT : ENTITY work.monotonic_counter(Behavioral) GENERIC MAP(STOP_COUNT => 88) PORT MAP(reset => reset, clock => clock, count => count);

	-- this process creates an artifitial clock with a 4 ns period
	clock_process : PROCESS (clock)
	BEGIN
		clock <= NOT clock AFTER 2 ns;
	END PROCESS;

	PROCESS
	BEGIN
		-- initial reset
		reset <= '1';
		WAIT FOR 5 ns;
		-- start of test
		reset <= '0';
		WAIT FOR 500 ns;
		WAIT;
	END PROCESS;

END Behavioral;

monotonic_counter/monotonic_counter.vcd
$date
  Thu Nov  3 13:53:34 2022
$end
$version
  GHDL v0
$end
$timescale
  1 fs
$end
$scope module standard $end
$upscope $end
$scope module std_logic_1164 $end
$upscope $end
$scope module numeric_std $end
$upscope $end
$scope module monotonic_counter_tb $end
$var reg 32 ! count[31:0] $end
$var reg 1 " clock $end
$var reg 1 # reset $end
$scope module uut $end
$var reg 1 $ reset $end
$var reg 1 % clock $end
$var reg 32 & count[31:0] $end
$var integer 32 ' n $end
$upscope $end
$upscope $end
$enddefinitions $end
#0
b00000000000000000000000000000000 !
0"
1#
1$
0%
b00000000000000000000000000000000 &
b0 '
#2000000
1"
1%
#4000000
0"
0%
#5000000
0#
0$
#6000000
b00000000000000000000000000000001 !
1"
1%
b00000000000000000000000000000001 &
b1 '
#8000000
0"
0%
#10000000
b00000000000000000000000000000010 !
1"
1%
b00000000000000000000000000000010 &
b10 '
#12000000
0"
0%
#14000000
b00000000000000000000000000000011 !
1"
1%
b00000000000000000000000000000011 &
b11 '
#16000000
0"
0%
#18000000
b00000000000000000000000000000100 !
1"
1%
b00000000000000000000000000000100 &
b100 '
#20000000
0"
0%
#22000000
b00000000000000000000000000000101 !
1"
1%
b00000000000000000000000000000101 &
b101 '
#24000000
0"
0%
#26000000
b00000000000000000000000000000110 !
1"
1%
b00000000000000000000000000000110 &
b110 '
#28000000
0"
0%
#30000000
b00000000000000000000000000000111 !
1"
1%
b00000000000000000000000000000111 &
b111 '
#32000000
0"
0%
#34000000
b00000000000000000000000000001000 !
1"
1%
b00000000000000000000000000001000 &
b1000 '
#36000000
0"
0%
#38000000
b00000000000000000000000000001001 !
1"
1%
b00000000000000000000000000001001 &
b1001 '
#40000000
0"
0%
#42000000
b00000000000000000000000000001010 !
1"
1%
b00000000000000000000000000001010 &
b1010 '
#44000000
0"
0%
#46000000
b00000000000000000000000000001011 !
1"
1%
b00000000000000000000000000001011 &
b1011 '
#48000000
0"
0%
#50000000
b00000000000000000000000000001100 !
1"
1%
b00000000000000000000000000001100 &
b1100 '
#52000000
0"
0%
#54000000
b00000000000000000000000000001101 !
1"
1%
b00000000000000000000000000001101 &
b1101 '
#56000000
0"
0%
#58000000
b00000000000000000000000000001110 !
1"
1%
b00000000000000000000000000001110 &
b1110 '
#60000000
0"
0%
#62000000
b00000000000000000000000000001111 !
1"
1%
b00000000000000000000000000001111 &
b1111 '
#64000000
0"
0%
#66000000
b00000000000000000000000000010000 !
1"
1%
b00000000000000000000000000010000 &
b10000 '
#68000000
0"
0%
#70000000
b00000000000000000000000000010001 !
1"
1%
b00000000000000000000000000010001 &
b10001 '
#72000000
0"
0%
#74000000
b00000000000000000000000000010010 !
1"
1%
b00000000000000000000000000010010 &
b10010 '
#76000000
0"
0%
#78000000
b00000000000000000000000000010011 !
1"
1%
b00000000000000000000000000010011 &
b10011 '
#80000000
0"
0%
#82000000
b00000000000000000000000000010100 !
1"
1%
b00000000000000000000000000010100 &
b10100 '
#84000000
0"
0%
#86000000
b00000000000000000000000000010101 !
1"
1%
b00000000000000000000000000010101 &
b10101 '
#88000000
0"
0%
#90000000
b00000000000000000000000000010110 !
1"
1%
b00000000000000000000000000010110 &
b10110 '
#92000000
0"
0%
#94000000
b00000000000000000000000000010111 !
1"
1%
b00000000000000000000000000010111 &
b10111 '
#96000000
0"
0%
#98000000
b00000000000000000000000000011000 !
1"
1%
b00000000000000000000000000011000 &
b11000 '
#100000000
0"
0%
#102000000
b00000000000000000000000000011001 !
1"
1%
b00000000000000000000000000011001 &
b11001 '
#104000000
0"
0%
#106000000
b00000000000000000000000000011010 !
1"
1%
b00000000000000000000000000011010 &
b11010 '
#108000000
0"
0%
#110000000
b00000000000000000000000000011011 !
1"
1%
b00000000000000000000000000011011 &
b11011 '
#112000000
0"
0%
#114000000
b00000000000000000000000000011100 !
1"
1%
b00000000000000000000000000011100 &
b11100 '
#116000000
0"
0%
#118000000
b00000000000000000000000000011101 !
1"
1%
b00000000000000000000000000011101 &
b11101 '
#120000000
0"
0%
#122000000
b00000000000000000000000000011110 !
1"
1%
b00000000000000000000000000011110 &
b11110 '
#124000000
0"
0%
#126000000
b00000000000000000000000000011111 !
1"
1%
b00000000000000000000000000011111 &
b11111 '
#128000000
0"
0%
#130000000
b00000000000000000000000000100000 !
1"
1%
b00000000000000000000000000100000 &
b100000 '
#132000000
0"
0%
#134000000
b00000000000000000000000000100001 !
1"
1%
b00000000000000000000000000100001 &
b100001 '
#136000000
0"
0%
#138000000
b00000000000000000000000000100010 !
1"
1%
b00000000000000000000000000100010 &
b100010 '
#140000000
0"
0%
#142000000
b00000000000000000000000000100011 !
1"
1%
b00000000000000000000000000100011 &
b100011 '
#144000000
0"
0%
#146000000
b00000000000000000000000000100100 !
1"
1%
b00000000000000000000000000100100 &
b100100 '
#148000000
0"
0%
#150000000
b00000000000000000000000000100101 !
1"
1%
b00000000000000000000000000100101 &
b100101 '
#152000000
0"
0%
#154000000
b00000000000000000000000000100110 !
1"
1%
b00000000000000000000000000100110 &
b100110 '
#156000000
0"
0%
#158000000
b00000000000000000000000000100111 !
1"
1%
b00000000000000000000000000100111 &
b100111 '
#160000000
0"
0%
#162000000
b00000000000000000000000000101000 !
1"
1%
b00000000000000000000000000101000 &
b101000 '
#164000000
0"
0%
#166000000
b00000000000000000000000000101001 !
1"
1%
b00000000000000000000000000101001 &
b101001 '
#168000000
0"
0%
#170000000
b00000000000000000000000000101010 !
1"
1%
b00000000000000000000000000101010 &
b101010 '
#172000000
0"
0%
#174000000
b00000000000000000000000000101011 !
1"
1%
b00000000000000000000000000101011 &
b101011 '
#176000000
0"
0%
#178000000
b00000000000000000000000000101100 !
1"
1%
b00000000000000000000000000101100 &
b101100 '
#180000000
0"
0%
#182000000
b00000000000000000000000000101101 !
1"
1%
b00000000000000000000000000101101 &
b101101 '
#184000000
0"
0%
#186000000
b00000000000000000000000000101110 !
1"
1%
b00000000000000000000000000101110 &
b101110 '
#188000000
0"
0%
#190000000
b00000000000000000000000000101111 !
1"
1%
b00000000000000000000000000101111 &
b101111 '
#192000000
0"
0%
#194000000
b00000000000000000000000000110000 !
1"
1%
b00000000000000000000000000110000 &
b110000 '
#196000000
0"
0%
#198000000
b00000000000000000000000000110001 !
1"
1%
b00000000000000000000000000110001 &
b110001 '
#200000000
0"
0%
#202000000
b00000000000000000000000000110010 !
1"
1%
b00000000000000000000000000110010 &
b110010 '
#204000000
0"
0%
#206000000
b00000000000000000000000000110011 !
1"
1%
b00000000000000000000000000110011 &
b110011 '
#208000000
0"
0%
#210000000
b00000000000000000000000000110100 !
1"
1%
b00000000000000000000000000110100 &
b110100 '
#212000000
0"
0%
#214000000
b00000000000000000000000000110101 !
1"
1%
b00000000000000000000000000110101 &
b110101 '
#216000000
0"
0%
#218000000
b00000000000000000000000000110110 !
1"
1%
b00000000000000000000000000110110 &
b110110 '
#220000000
0"
0%
#222000000
b00000000000000000000000000110111 !
1"
1%
b00000000000000000000000000110111 &
b110111 '
#224000000
0"
0%
#226000000
b00000000000000000000000000111000 !
1"
1%
b00000000000000000000000000111000 &
b111000 '
#228000000
0"
0%
#230000000
b00000000000000000000000000111001 !
1"
1%
b00000000000000000000000000111001 &
b111001 '
#232000000
0"
0%
#234000000
b00000000000000000000000000111010 !
1"
1%
b00000000000000000000000000111010 &
b111010 '
#236000000
0"
0%
#238000000
b00000000000000000000000000111011 !
1"
1%
b00000000000000000000000000111011 &
b111011 '
#240000000
0"
0%
#242000000
b00000000000000000000000000111100 !
1"
1%
b00000000000000000000000000111100 &
b111100 '
#244000000
0"
0%
#246000000
b00000000000000000000000000111101 !
1"
1%
b00000000000000000000000000111101 &
b111101 '
#248000000
0"
0%
#250000000
b00000000000000000000000000111110 !
1"
1%
b00000000000000000000000000111110 &
b111110 '
#252000000
0"
0%
#254000000
b00000000000000000000000000111111 !
1"
1%
b00000000000000000000000000111111 &
b111111 '
#256000000
0"
0%
#258000000
b00000000000000000000000001000000 !
1"
1%
b00000000000000000000000001000000 &
b1000000 '
#260000000
0"
0%
#262000000
b00000000000000000000000001000001 !
1"
1%
b00000000000000000000000001000001 &
b1000001 '
#264000000
0"
0%
#266000000
b00000000000000000000000001000010 !
1"
1%
b00000000000000000000000001000010 &
b1000010 '
#268000000
0"
0%
#270000000
b00000000000000000000000001000011 !
1"
1%
b00000000000000000000000001000011 &
b1000011 '
#272000000
0"
0%
#274000000
b00000000000000000000000001000100 !
1"
1%
b00000000000000000000000001000100 &
b1000100 '
#276000000
0"
0%
#278000000
b00000000000000000000000001000101 !
1"
1%
b00000000000000000000000001000101 &
b1000101 '
#280000000
0"
0%
#282000000
b00000000000000000000000001000110 !
1"
1%
b00000000000000000000000001000110 &
b1000110 '
#284000000
0"
0%
#286000000
b00000000000000000000000001000111 !
1"
1%
b00000000000000000000000001000111 &
b1000111 '
#288000000
0"
0%
#290000000
b00000000000000000000000001001000 !
1"
1%
b00000000000000000000000001001000 &
b1001000 '
#292000000
0"
0%
#294000000
b00000000000000000000000001001001 !
1"
1%
b00000000000000000000000001001001 &
b1001001 '
#296000000
0"
0%
#298000000
b00000000000000000000000001001010 !
1"
1%
b00000000000000000000000001001010 &
b1001010 '
#300000000
0"
0%
#302000000
b00000000000000000000000001001011 !
1"
1%
b00000000000000000000000001001011 &
b1001011 '
#304000000
0"
0%
#306000000
b00000000000000000000000001001100 !
1"
1%
b00000000000000000000000001001100 &
b1001100 '
#308000000
0"
0%
#310000000
b00000000000000000000000001001101 !
1"
1%
b00000000000000000000000001001101 &
b1001101 '
#312000000
0"
0%
#314000000
b00000000000000000000000001001110 !
1"
1%
b00000000000000000000000001001110 &
b1001110 '
#316000000
0"
0%
#318000000
b00000000000000000000000001001111 !
1"
1%
b00000000000000000000000001001111 &
b1001111 '
#320000000
0"
0%
#322000000
b00000000000000000000000001010000 !
1"
1%
b00000000000000000000000001010000 &
b1010000 '
#324000000
0"
0%
#326000000
b00000000000000000000000001010001 !
1"
1%
b00000000000000000000000001010001 &
b1010001 '
#328000000
0"
0%
#330000000
b00000000000000000000000001010010 !
1"
1%
b00000000000000000000000001010010 &
b1010010 '
#332000000
0"
0%
#334000000
b00000000000000000000000001010011 !
1"
1%
b00000000000000000000000001010011 &
b1010011 '
#336000000
0"
0%
#338000000
b00000000000000000000000001010100 !
1"
1%
b00000000000000000000000001010100 &
b1010100 '
#340000000
0"
0%
#342000000
b00000000000000000000000001010101 !
1"
1%
b00000000000000000000000001010101 &
b1010101 '
#344000000
0"
0%
#346000000
b00000000000000000000000001010110 !
1"
1%
b00000000000000000000000001010110 &
b1010110 '
#348000000
0"
0%
#350000000
b00000000000000000000000001010111 !
1"
1%
b00000000000000000000000001010111 &
b1010111 '
#352000000
0"
0%
#354000000
b00000000000000000000000001011000 !
1"
1%
b00000000000000000000000001011000 &
b1011000 '
#356000000
0"
0%
#358000000
b00000000000000000000000000000000 !
1"
1%
b00000000000000000000000000000000 &
b0 '
#360000000
0"
0%
#362000000
b00000000000000000000000000000001 !
1"
1%
b00000000000000000000000000000001 &
b1 '
#364000000
0"
0%
#366000000
b00000000000000000000000000000010 !
1"
1%
b00000000000000000000000000000010 &
b10 '
#368000000
0"
0%
#370000000
b00000000000000000000000000000011 !
1"
1%
b00000000000000000000000000000011 &
b11 '
#372000000
0"
0%
#374000000
b00000000000000000000000000000100 !
1"
1%
b00000000000000000000000000000100 &
b100 '
#376000000
0"
0%
#378000000
b00000000000000000000000000000101 !
1"
1%
b00000000000000000000000000000101 &
b101 '
#380000000
0"
0%
#382000000
b00000000000000000000000000000110 !
1"
1%
b00000000000000000000000000000110 &
b110 '
#384000000
0"
0%
#386000000
b00000000000000000000000000000111 !
1"
1%
b00000000000000000000000000000111 &
b111 '
#388000000
0"
0%
#390000000
b00000000000000000000000000001000 !
1"
1%
b00000000000000000000000000001000 &
b1000 '
#392000000
0"
0%
#394000000
b00000000000000000000000000001001 !
1"
1%
b00000000000000000000000000001001 &
b1001 '
#396000000
0"
0%
#398000000
b00000000000000000000000000001010 !
1"
1%
b00000000000000000000000000001010 &
b1010 '
#400000000
0"
0%
#402000000
b00000000000000000000000000001011 !
1"
1%
b00000000000000000000000000001011 &
b1011 '
#404000000
0"
0%
#406000000
b00000000000000000000000000001100 !
1"
1%
b00000000000000000000000000001100 &
b1100 '
#408000000
0"
0%
#410000000
b00000000000000000000000000001101 !
1"
1%
b00000000000000000000000000001101 &
b1101 '
#412000000
0"
0%
#414000000
b00000000000000000000000000001110 !
1"
1%
b00000000000000000000000000001110 &
b1110 '
#416000000
0"
0%
#418000000
b00000000000000000000000000001111 !
1"
1%
b00000000000000000000000000001111 &
b1111 '
#420000000
0"
0%
#422000000
b00000000000000000000000000010000 !
1"
1%
b00000000000000000000000000010000 &
b10000 '
#424000000
0"
0%
#426000000
b00000000000000000000000000010001 !
1"
1%
b00000000000000000000000000010001 &
b10001 '
#428000000
0"
0%
#430000000
b00000000000000000000000000010010 !
1"
1%
b00000000000000000000000000010010 &
b10010 '
#432000000
0"
0%
#434000000
b00000000000000000000000000010011 !
1"
1%
b00000000000000000000000000010011 &
b10011 '
#436000000
0"
0%
#438000000
b00000000000000000000000000010100 !
1"
1%
b00000000000000000000000000010100 &
b10100 '
#440000000
0"
0%
#442000000
b00000000000000000000000000010101 !
1"
1%
b00000000000000000000000000010101 &
b10101 '
#444000000
0"
0%
#446000000
b00000000000000000000000000010110 !
1"
1%
b00000000000000000000000000010110 &
b10110 '
#448000000
0"
0%
#450000000
b00000000000000000000000000010111 !
1"
1%
b00000000000000000000000000010111 &
b10111 '
#452000000
0"
0%
#454000000
b00000000000000000000000000011000 !
1"
1%
b00000000000000000000000000011000 &
b11000 '
#456000000
0"
0%
#458000000
b00000000000000000000000000011001 !
1"
1%
b00000000000000000000000000011001 &
b11001 '
#460000000
0"
0%
#462000000
b00000000000000000000000000011010 !
1"
1%
b00000000000000000000000000011010 &
b11010 '
#464000000
0"
0%
#466000000
b00000000000000000000000000011011 !
1"
1%
b00000000000000000000000000011011 &
b11011 '
#468000000
0"
0%
#470000000
b00000000000000000000000000011100 !
1"
1%
b00000000000000000000000000011100 &
b11100 '
#472000000
0"
0%
#474000000
b00000000000000000000000000011101 !
1"
1%
b00000000000000000000000000011101 &
b11101 '
#476000000
0"
0%
#478000000
b00000000000000000000000000011110 !
1"
1%
b00000000000000000000000000011110 &
b11110 '
#480000000
0"
0%
#482000000
b00000000000000000000000000011111 !
1"
1%
b00000000000000000000000000011111 &
b11111 '
#484000000
0"
0%
#486000000
b00000000000000000000000000100000 !
1"
1%
b00000000000000000000000000100000 &
b100000 '
#488000000
0"
0%
#490000000
b00000000000000000000000000100001 !
1"
1%
b00000000000000000000000000100001 &
b100001 '
#492000000
0"
0%
#494000000
b00000000000000000000000000100010 !
1"
1%
b00000000000000000000000000100010 &
b100010 '
#496000000
0"
0%
#498000000
b00000000000000000000000000100011 !
1"
1%
b00000000000000000000000000100011 &
b100011 '
#500000000
0"
0%
#502000000
b00000000000000000000000000100100 !
1"
1%
b00000000000000000000000000100100 &
b100100 '
#504000000
0"
0%
#505000000
#506000000
b00000000000000000000000000100101 !
1"
1%
b00000000000000000000000000100101 &
b100101 '
#508000000
0"
0%
#510000000
b00000000000000000000000000100110 !
1"
1%
b00000000000000000000000000100110 &
b100110 '
#512000000
0"
0%
#514000000
b00000000000000000000000000100111 !
1"
1%
b00000000000000000000000000100111 &
b100111 '
#516000000
0"
0%
#518000000
b00000000000000000000000000101000 !
1"
1%
b00000000000000000000000000101000 &
b101000 '
#520000000
0"
0%
#522000000
b00000000000000000000000000101001 !
1"
1%
b00000000000000000000000000101001 &
b101001 '
#524000000
0"
0%
#526000000
b00000000000000000000000000101010 !
1"
1%
b00000000000000000000000000101010 &
b101010 '
#528000000
0"
0%
#530000000
b00000000000000000000000000101011 !
1"
1%
b00000000000000000000000000101011 &
b101011 '
#532000000
0"
0%
#534000000
b00000000000000000000000000101100 !
1"
1%
b00000000000000000000000000101100 &
b101100 '
#536000000
0"
0%
#538000000
b00000000000000000000000000101101 !
1"
1%
b00000000000000000000000000101101 &
b101101 '
#540000000
0"
0%
#542000000
b00000000000000000000000000101110 !
1"
1%
b00000000000000000000000000101110 &
b101110 '
#544000000
0"
0%
#546000000
b00000000000000000000000000101111 !
1"
1%
b00000000000000000000000000101111 &
b101111 '
#548000000
0"
0%
#550000000
b00000000000000000000000000110000 !
1"
1%
b00000000000000000000000000110000 &
b110000 '
#552000000
0"
0%
#554000000
b00000000000000000000000000110001 !
1"
1%
b00000000000000000000000000110001 &
b110001 '
#556000000
0"
0%
#558000000
b00000000000000000000000000110010 !
1"
1%
b00000000000000000000000000110010 &
b110010 '
#560000000
0"
0%
#562000000
b00000000000000000000000000110011 !
1"
1%
b00000000000000000000000000110011 &
b110011 '
#564000000
0"
0%
#566000000
b00000000000000000000000000110100 !
1"
1%
b00000000000000000000000000110100 &
b110100 '
#568000000
0"
0%
#570000000
b00000000000000000000000000110101 !
1"
1%
b00000000000000000000000000110101 &
b110101 '
#572000000
0"
0%
#574000000
b00000000000000000000000000110110 !
1"
1%
b00000000000000000000000000110110 &
b110110 '
#576000000
0"
0%
#578000000
b00000000000000000000000000110111 !
1"
1%
b00000000000000000000000000110111 &
b110111 '
#580000000
0"
0%
#582000000
b00000000000000000000000000111000 !
1"
1%
b00000000000000000000000000111000 &
b111000 '
#584000000
0"
0%
#586000000
b00000000000000000000000000111001 !
1"
1%
b00000000000000000000000000111001 &
b111001 '
#588000000
0"
0%
#590000000
b00000000000000000000000000111010 !
1"
1%
b00000000000000000000000000111010 &
b111010 '
#592000000
0"
0%
#594000000
b00000000000000000000000000111011 !
1"
1%
b00000000000000000000000000111011 &
b111011 '
#596000000
0"
0%
#598000000
b00000000000000000000000000111100 !
1"
1%
b00000000000000000000000000111100 &
b111100 '
