mux/mux_4.vhdl
----------------------------------------------------------------------------------
-- Filename : mux_4.vhdl
-- Author : Antonio Alejandro Andara Lara
-- Date : 28-Oct-10-2022
-- Design Name: mux_4
-- Module Name: combinational circuits
-- Project Name: VHDL_essentials
-- Description : Example of a 4:1 multiplexer
-- Additional Comments:
-- Copyright : University of Alberta, 2022
-- License : CC0 1.0 Universal
----------------------------------------------------------------------------------

LIBRARY IEEE;
USE IEEE.STD_LOGIC_1164.ALL;

ENTITY mux_4 IS
    PORT (
        d0, d1, d2, d3 : IN STD_LOGIC;
        sel            : IN STD_LOGIC_VECTOR(1 DOWNTO 0);
        mux_out        : OUT STD_LOGIC
    );
END ENTITY mux_4;

ARCHITECTURE Behavioral OF mux_4 IS
BEGIN
    WITH (sel) SELECT
    mux_out <= d0 WHEN "00",
        d1 WHEN "01",
        d2 WHEN "10",
        d3 WHEN "11",
        'X' WHEN OTHERS;
END Behavioral;

mux/mux_4_tb.vhdl
----------------------------------------------------------------------------------
-- Filename : mux_4_tb.vhdl
-- Author : Antonio Alejandro Andara Lara
-- Date : 28-Oct-10-2022
-- Design Name: mux_4_tb
-- Module Name: combinational circuits
-- Project Name: VHDL_essentials
-- Description : Testbench for 4:1 multiplexer
-- Additional Comments:
-- Copyright : University of Alberta, 2022
-- License : CC0 1.0 Universal
----------------------------------------------------------------------------------
LIBRARY IEEE;
USE IEEE.STD_LOGIC_1164.ALL;

ENTITY mux_4_tb IS
    --  empty
END mux_4_tb;

ARCHITECTURE Behavioral OF mux_4_tb IS

    SIGNAL d0, d1, d2, d3, mux_out : STD_LOGIC                    := '0';
    SIGNAL sel                     : STD_LOGIC_VECTOR(1 DOWNTO 0) := "00";

BEGIN
    -- Direct entity instantiation
    DUT : ENTITY work.mux_4(Behavioral) PORT MAP(d0 => d0, d1 => d1, d2 => d2, d3 => d3, sel => sel, mux_out => mux_out);

    stimulus : PROCESS
    BEGIN
        WAIT FOR 2 ns;
        d0 <= '1';
        d1 <= '0';
        d2 <= '1';
        d3 <= '0';
        WAIT FOR 2 ns;
        sel <= "01";
        WAIT FOR 2 ns;
        sel <= "10";
        WAIT FOR 2 ns;
        sel <= "11";
        WAIT FOR 2 ns;
        d0  <= '0';
        d1  <= '1';
        d2  <= '0';
        d3  <= '1';
        sel <= "00";
        WAIT FOR 2 ns;
        sel <= "01";
        WAIT FOR 2 ns;
        sel <= "10";
        WAIT FOR 2 ns;
        sel <= "11";
        WAIT FOR 2 ns;
        WAIT;
    END PROCESS;
END Behavioral;

mux/mux_4.vcd
$date
  Thu Nov  3 14:13:11 2022
$end
$version
  GHDL v0
$end
$timescale
  1 fs
$end
$scope module standard $end
$upscope $end
$scope module std_logic_1164 $end
$upscope $end
$scope module mux_4_tb $end
$var reg 1 ! d0 $end
$var reg 1 " d1 $end
$var reg 1 # d2 $end
$var reg 1 $ d3 $end
$var reg 1 % mux_out $end
$var reg 2 & sel[1:0] $end
$scope module dut $end
$var reg 1 ' d0 $end
$var reg 1 ( d1 $end
$var reg 1 ) d2 $end
$var reg 1 * d3 $end
$var reg 2 + sel[1:0] $end
$var reg 1 , mux_out $end
$upscope $end
$upscope $end
$enddefinitions $end
#0
0!
0"
0#
0$
0%
b00 &
0'
0(
0)
0*
b00 +
0,
#2000000
1!
1#
1%
1'
1)
1,
#4000000
0%
b01 &
b01 +
0,
#6000000
1%
b10 &
b10 +
1,
#8000000
0%
b11 &
b11 +
0,
#10000000
0!
1"
0#
1$
b00 &
0'
1(
0)
1*
b00 +
#12000000
1%
b01 &
b01 +
1,
#14000000
0%
b10 &
b10 +
0,
#16000000
1%
b11 &
b11 +
1,
