keypad_driver/clock_divider.vhdl
----------------------------------------------------------------------------------
-- Filename : clock_divider.vhdl
-- Author : Antonio Alejandro Andara Lara
-- Date : 06-Nov-10-2022
-- Design Name: clock divider
-- Module Name: VHDL_essentials
-- Project Name: VHDL_essentials
-- Description : In this file we will implement a clock divider, a very useful component
--  and a fundamental block for many projects
-- Additional Comments: Our clock divider will take two generic parameters (the frequencies of the
-- input and output clock signals in Hz) and the output will be the desired output frequency,
-- the divider performs the inner calculation to match the frequencies.
-- Copyright : University of Alberta, 2022
-- License : CC0 1.0 Universal
----------------------------------------------------------------------------------

LIBRARY IEEE;
USE IEEE.STD_LOGIC_1164.ALL;

-- the value 2*freq_out must be a divisor of freq_in in
-- order to avoid drifting of the clock signals
ENTITY clock_divider IS
    GENERIC (
        freq_in : INTEGER := 125_000_000; -- input clock frequency in Hz
        freq_out     : INTEGER := 1_000 -- output clock frequency in Hz
        );
    -- examples of integer dividers for the inner clock of the zybo z7 B board:
    -- 1, 2, 4, 5, 8, 10, 16, 20, 25, 32, 40, 50, 80, 100,
    -- 125, 160, 200, 250, 400, 500, 625, 800, 1_000, 1_250,
    -- 2_000, 2_500, 3_125, 4_000, 5_000, 6_250, 10_000, 12_500,
    -- 15_625, 20_000, 25_000, 31_250, 50_000, 62_500,
    -- 78_125, 100_000, 125_000, 156_250, 250_000, 500_000
    PORT (
        clock     : IN STD_LOGIC; -- input clock signal
        clock_div : OUT STD_LOGIC -- output clock signal
        );
END clock_divider;

ARCHITECTURE Behavioral OF clock_divider IS

    -- calculate counter limit
    CONSTANT limit : INTEGER := freq_in/(2*freq_out);

    --signals for the counter
    SIGNAL count        : INTEGER RANGE 1 TO limit:=1; -- set the counter range
    SIGNAL clock_signal : STD_LOGIC := '0';

BEGIN
    clock_div <= clock_signal; -- direct output asignment

    -- this implementation is very straightforward, we want to increment the
    -- counter on every rising edge until it reaches its limit value,
    -- then we reset the counter and flip the value of the output
    PROCESS (clock)
    BEGIN
        IF rising_edge(clock) THEN
            IF count < limit THEN
                count <= count + 1;
            ELSE
                count        <= 1;
                clock_signal <= NOT clock_signal;
            END IF;
        END IF;
    END PROCESS;
END Behavioral;

keypad_driver/display_controller.vhdl
----------------------------------------------------------------------------------
-- Filename : display_controller.vhdl
-- Author : Antonio Alejandro Andara Lara
-- Date : 06-Nov-10-2022
-- Design Name: display controller
-- Module Name: VHDL_essentials
-- Project Name: VHDL_essentials
-- Description : In this file we will implement a design that can read two 4 bit
-- characters from a register and show it on the appropriate seven segments display
-- Additional Comments:
-- Copyright : University of Alberta, 2022
-- License : CC0 1.0 Universal
----------------------------------------------------------------------------------

LIBRARY IEEE;
USE IEEE.STD_LOGIC_1164.ALL;
USE IEEE.NUMERIC_STD.ALL;

ENTITY display_controller IS
	PORT (
		-- read in digits, the 4 MSBs represent the first digit
		-- the last LSBs represent, the sencond digit
		digits : IN STD_LOGIC_VECTOR (7 DOWNTO 0);
		clock  : IN STD_LOGIC;
		-- Controls which of the seven segment displays is active
		display_select : OUT STD_LOGIC := '0';
		--controls which digit to display
		segments : OUT STD_LOGIC_VECTOR (6 DOWNTO 0)
	);
END display_controller;

ARCHITECTURE Behavioral OF display_controller IS
	-- this signal will get the value of the character to display
	SIGNAL digit : STD_LOGIC_VECTOR (3 DOWNTO 0);

BEGIN

	display_select <= clock;

	WITH clock SELECT
		digit <= digits(7 DOWNTO 4) WHEN '1',
		digits(3 DOWNTO 0) WHEN OTHERS;

	-- the zybo z7 Pmod SSD: Seven Segment Display
	-- is attached to the board in such a way that
	-- the characters look upside down if we follow the
	-- mapping from the manual, for this reason we use
	-- a different mapping that solves this problem.
	WITH digit SELECT -- segments "ABCDEFG" 
		segments <= "1111110" WHEN "0000", --0
					"0000110" WHEN "0001", --1
					"1101101" WHEN "0010", --2
					"1001111" WHEN "0011", --3
					"0010111" WHEN "0100", --4
					"1011011" WHEN "0101", --5
					"1111011" WHEN "0110", --6
					"0001110" WHEN "0111", --7
					"1111111" WHEN "1000", --8
					"1011111" WHEN "1001", --9
					"0111111" WHEN "1010", --A
					"1110011" WHEN "1011", --B
					"1111000" WHEN "1100", --C
					"1100111" WHEN "1101", --D
					"1111001" WHEN "1110", --E
					"0111001" WHEN "1111", --F
					"0000000" WHEN OTHERS;
END Behavioral;

keypad_driver/keypad_register.vhdl
----------------------------------------------------------------------------------
-- Filename : keypad_register.vhdl
-- Author : Antonio Alejandro Andara Lara
-- Date : 06-Nov-10-2022
-- Design Name: keypad register
-- Module Name: VHDL_essentials
-- Project Name: VHDL_essentials
-- Description : In this file we will implement a simple shift register to store
-- values coming from a keypad or any other 4 bit input
-- Additional Comments: for this design we require a register that can store
-- the last 2 received values and also need a way to prevent multiple updates
-- in succesion, for this we use a flag signal that is raised with every update
-- and it's only lowered after a certain amount of time has passed, this time
-- can be changed by changing the count variable
-- Copyright : University of Alberta, 2022
-- License : CC0 1.0 Universal
----------------------------------------------------------------------------------

LIBRARY IEEE;
USE IEEE.STD_LOGIC_1164.ALL;
USE IEEE.NUMERIC_STD;

ENTITY keypad_register IS
    PORT (
        clock  : IN STD_LOGIC;
        value  : IN STD_LOGIC_VECTOR(4 DOWNTO 0)  := (OTHERS => '0');
        digits : OUT STD_LOGIC_VECTOR(7 DOWNTO 0) := (OTHERS => '0');
        locked : OUT STD_LOGIC
    );
END;

ARCHITECTURE Behavioral OF keypad_register IS
    SIGNAL aux: STD_LOGIC_VECTOR(7 downto 0);
    SIGNAL count : INTEGER := 0;
    SIGNAL flag: STD_LOGIC:='0';
BEGIN
    locked <= flag;
    digits <= aux;

    PROCESS (clock)
    BEGIN
        IF rising_edge(clock) THEN
            -- update event. set count and raise flag
            IF value(4) = '0' AND flag = '0' THEN
                aux(3 DOWNTO 0) <= aux(7 DOWNTO 4);
                aux(7 DOWNTO 4) <= value(3 DOWNTO 0);
                count           <= 250;
                flag            <= '1';
                -- output locked, a change in the input won't
                -- have effect on the output during this time.
            ELSIF count > 0 THEN
                count <= count - 1;
            ELSIF count = 0 THEN
                flag <= '0';
            END IF;
        END IF;
    END PROCESS;
END Behavioral;

keypad_driver/keypad_decoder.vhdl
--------------------------------------------------------------------------------
-- Filename : keypad_decoder.vhdl
-- Author : Antonio Alejandro Andara Lara
-- Date : 06-Nov-10-2022
-- Design Name: keypad decoder
-- Module Name: VHDL_essentials
-- Project Name: VHDL_essentials
-- Description : Design for a 4x4 matrix keypad decoder
-- Additional Comments: input clock signal = 1 kHz
-- Copyright : University of Alberta, 2022
-- License : CC0 1.0 Universal
--------------------------------------------------------------------------------

LIBRARY IEEE;
USE IEEE.STD_LOGIC_1164.ALL;
USE IEEE.NUMERIC_STD.ALL; -- only neccesary if using the rotate function

-- the keypad decoder automatically goes trough the input rows
-- one at a time and checks if the output value of the columns
-- matches with a button.

ENTITY keypad_decoder IS
    PORT (
        clock    : IN STD_LOGIC;
        row      : IN STD_LOGIC_VECTOR (3 DOWNTO 0);
        column   : OUT STD_LOGIC_VECTOR (3 DOWNTO 0);
        data_out : OUT STD_LOGIC_VECTOR (4 DOWNTO 0));
END keypad_decoder;

ARCHITECTURE Behavioral OF keypad_decoder IS

    SIGNAL sclk : STD_LOGIC_VECTOR (3 DOWNTO 0) := "0111"; -- this sets the initial value for the rows input
    -- if the MSB of this signal is '1' it indicates an invalid character
    SIGNAL aux  : STD_LOGIC_VECTOR (4 DOWNTO 0) := "00000";

BEGIN
    column   <= sclk;
    data_out <= aux;

    PROCESS (clock)
    BEGIN
        IF clock'event AND clock = '1' THEN
            -- scan columns
            CASE sclk IS
                WHEN "0111" => --Column 1
                    CASE row IS
                        WHEN "0111" => aux <= "00001"; --1
                        WHEN "1011" => aux <= "00100"; --4
                        WHEN "1101" => aux <= "00111"; --7
                        WHEN "1110" => aux <= "00000"; --0
                        WHEN OTHERS => aux <= "10000"; -- invalid
                    END CASE;
                WHEN "1011" => --Column 2
                    CASE row IS
                        WHEN "0111" => aux <= "00010"; --2
                        WHEN "1011" => aux <= "00101"; --5
                        WHEN "1101" => aux <= "01000"; --8
                        WHEN "1110" => aux <= "01111"; --F
                        WHEN OTHERS => aux <= "10000"; -- invalid
                    END CASE;
                WHEN "1101" => --Column 3
                    CASE row IS
                        WHEN "0111" => aux <= "00011"; --3
                        WHEN "1011" => aux <= "00110"; --6
                        WHEN "1101" => aux <= "01001"; --9
                        WHEN "1110" => aux <= "01110"; --E
                        WHEN OTHERS => aux <= "10000"; -- invalid
                    END CASE;
                WHEN "1110" => --Column 4
                    CASE row IS
                        WHEN "0111" => aux <= "01010"; --A
                        WHEN "1011" => aux <= "01011"; --B
                        WHEN "1101" => aux <= "01100"; --C
                        WHEN "1110" => aux <= "01101"; --D
                        WHEN OTHERS => aux <= "10000"; -- invalid
                    END CASE;
                WHEN OTHERS => aux <= "10000"; -- invalid
            END CASE;

        END IF;

        IF clock'event AND clock = '0' THEN
            -- rotate rows
            sclk <= sclk(2 DOWNTO 0) & sclk(3);

            -- another way of achieving the same result using a function instead
            -- sclk <= std_logic_vector(rotate_left(unsigned(sclk), 1));
        END IF;

    END PROCESS;
END Behavioral;

keypad_driver/keypad_driver.vhdl
----------------------------------------------------------------------------------
-- Filename : keypad_driver.vhdl
-- Author : Antonio Alejandro Andara Lara
-- Date : 06-Nov-10-2022
-- Design Name: keypad driver
-- Module Name: VHDL_essentials
-- Project Name: VHDL_essentials
-- Description : In this file we will implement a design that can read, store,
-- and display the values coming in from a 4x4 matrix keypad
-- Additional Comments: for this design we will use two clock dividers (one for
-- the keypad decoder and one for the display driver), an 8 bit register that
-- will store the last 2 received values and a display controller that will
-- show the contents of the register on the 7 segments diplays
-- Copyright : University of Alberta, 2022
-- License : CC0 1.0 Universal
----------------------------------------------------------------------------------

LIBRARY IEEE;
USE IEEE.STD_LOGIC_1164.ALL;

ENTITY keypad_driver IS
    PORT (
        clock          : IN STD_LOGIC := '1';
        row            : IN STD_LOGIC_VECTOR(3 DOWNTO 0);            -- keypad rows "123A" "456B" "789C" "0FED"
        column         : OUT STD_LOGIC_VECTOR(3 DOWNTO 0) := "0111"; -- keypad columns "1470" "258F" "369E" "ABCD"
        display_select : OUT STD_LOGIC;                              -- Controls which of the seven segment displays is active
        locked         : OUT STD_LOGIC;                              -- if '1' the keypad value is locked
        leds           : OUT STD_LOGIC_VECTOR(3 DOWNTO 0);
        segments       : OUT STD_LOGIC_VECTOR (6 DOWNTO 0) -- active segments on the seven segment display 
        );
END keypad_driver;

ARCHITECTURE Structural OF keypad_driver IS
    SIGNAL decoder_clock, display_clock : STD_LOGIC;
    SIGNAL value                        : STD_LOGIC_VECTOR (4 DOWNTO 0);
    SIGNAL digits                       : STD_LOGIC_VECTOR (7 DOWNTO 0);

BEGIN
    -- main components
    keypad_decoder    : ENTITY WORK.keypad_decoder(Behavioral) PORT MAP (clock=>decoder_clock,row=>row,column=>column,data_out=>value);
    keypad_register   : ENTITY WORK.keypad_register(Behavioral) PORT MAP (locked=>locked,value=>value,clock=>decoder_clock,digits=>digits);
    keypad_display    : ENTITY WORK.display_controller(Behavioral) PORT MAP (digits=>digits,clock=>display_clock,display_select=>display_select,segments=>segments);
    -- clock dividers (multiply frequencies by 1000 when simulating in order to save memory and time)
    decoder_div : ENTITY WORK.clock_divider(Behavioral) GENERIC MAP (freq_out => 10000000) PORT MAP(clock=>clock,clock_div=>decoder_clock);
    display_div : ENTITY WORK.clock_divider(Behavioral) GENERIC MAP (freq_out => 500000) PORT MAP(clock=>clock,clock_div=>display_clock);
    -- this will show the value read byt the keypad value on the leds in real time
    leds <= value(3 DOWNTO 0);
END;

keypad_driver/keypad_tb.vhdl
--------------------------------------------------------------------------------
-- Filename : keypad_tb.vhdl
-- Author : Antonio Alejandro Andara Lara
-- Date : 06-Nov-10-2022
-- Design Name: keypad tb
-- Module Name: VHDL_essentials
-- Project Name: VHDL_essentials
-- Description : This file implements a simple testbench
-- for our keypad driver design
-- Additional Comments: to get the most out of the simulation it is advisable
-- to multiply the input frequencies of the dividers by 100, this will decrease
-- the time needed to see the results in the simulation as well as the memory
-- Copyright : University of Alberta, 2022
-- License : CC0 1.0 Universal
--------------------------------------------------------------------------------

LIBRARY IEEE;
USE IEEE.STD_LOGIC_1164.ALL;


ENTITY keypad_tb IS
-- empty
END keypad_tb;

ARCHITECTURE Behavioral OF keypad_tb IS

    SIGNAL clock          : STD_LOGIC                     := '0';
    SIGNAL row            : STD_LOGIC_VECTOR(3 DOWNTO 0)  := "0000";
    SIGNAL column         : STD_LOGIC_VECTOR(3 DOWNTO 0)  := "0000";
    SIGNAL display_select : STD_LOGIC                     := '0';
    SIGNAL locked         : STD_LOGIC                     := '0';
    SIGNAL leds           : STD_LOGIC_VECTOR(3 DOWNTO 0)  := (OTHERS => '0');
    SIGNAL segments       : STD_LOGIC_VECTOR (6 DOWNTO 0) := "0000000";

    -- I'm using indirect instantiation here as an example
    COMPONENT keypad_driver IS
        PORT (
            clock          : IN STD_LOGIC                     := '0';
            row            : IN STD_LOGIC_VECTOR(3 DOWNTO 0)  := "UUUU";
            column         : OUT STD_LOGIC_VECTOR(3 DOWNTO 0) := "UUUU";
            display_select : OUT STD_LOGIC                    := '0';
            locked         : OUT STD_LOGIC;
            leds           : OUT STD_LOGIC_VECTOR(3 DOWNTO 0);
            segments       : OUT STD_LOGIC_VECTOR (6 DOWNTO 0) := "0000000"
        );
    END COMPONENT;

BEGIN
    DUT : keypad_driver PORT MAP(clock => clock, row => row, column => column, display_select => display_select, segments => segments);

    clock_process : PROCESS (clock)
    BEGIN
        clock <= NOT clock AFTER 4 ns;
    END PROCESS;

    stimulus : PROCESS
    BEGIN
        WAIT FOR 26 us;
        WAIT FOR 150 ns;
        row <= "0111";
        WAIT FOR 25 us;
        row <= "0000";
        WAIT FOR 15 us;
        WAIT;
    END PROCESS;
END;

keypad_driver/vcd_keypad.vcd
$date
  Thu Nov 17 12:21:09 2022
$end
$version
  GHDL v0
$end
$timescale
  1 fs
$end
$scope module standard $end
$upscope $end
$scope module std_logic_1164 $end
$upscope $end
$scope module numeric_std $end
$upscope $end
$scope module keypad_tb $end
$var reg 1 ! clock $end
$var reg 4 " row[3:0] $end
$var reg 4 # column[3:0] $end
$var reg 1 $ display_select $end
$var reg 1 % locked $end
$var reg 4 & leds[3:0] $end
$var reg 7 ' segments[6:0] $end
$scope module dut $end
$var reg 1 ( clock $end
$var reg 4 ) row[3:0] $end
$var reg 4 * column[3:0] $end
$var reg 1 + display_select $end
$var reg 1 , locked $end
$var reg 4 - leds[3:0] $end
$var reg 7 . segments[6:0] $end
$var reg 1 / decoder_clock $end
$var reg 1 0 display_clock $end
$var reg 5 1 value[4:0] $end
$var reg 8 2 digits[7:0] $end
$scope module keypad_decoder $end
$var reg 1 3 clock $end
$var reg 4 4 row[3:0] $end
$var reg 4 5 column[3:0] $end
$var reg 5 6 data_out[4:0] $end
$var reg 4 7 sclk[3:0] $end
$var reg 5 8 aux[4:0] $end
$upscope $end
$scope module keypad_register $end
$var reg 1 9 clock $end
$var reg 5 : value[4:0] $end
$var reg 8 ; digits[7:0] $end
$var reg 1 < locked $end
$var reg 8 = aux[7:0] $end
$var integer 32 > count $end
$var reg 1 ? flag $end
$upscope $end
$scope module keypad_display $end
$var reg 8 @ digits[7:0] $end
$var reg 1 A clock $end
$var reg 1 B display_select $end
$var reg 7 C segments[6:0] $end
$var reg 4 D digit[3:0] $end
$upscope $end
$scope module decoder_div $end
$var reg 1 E clock $end
$var reg 1 F clock_div $end
$var integer 32 G count $end
$var reg 1 H clock_signal $end
$upscope $end
$scope module display_div $end
$var reg 1 I clock $end
$var reg 1 J clock_div $end
$var integer 32 K count $end
$var reg 1 L clock_signal $end
$upscope $end
$upscope $end
$upscope $end
$enddefinitions $end
#0
0!
b0000 "
b1110 #
0$
0%
b0000 &
b0000000 '
0(
b0000 )
b1110 *
0+
0,
b0000 -
b0000000 .
0/
00
b00000 1
bUUUUUUUU 2
03
b0000 4
b1110 5
b00000 6
b1110 7
b00000 8
09
b00000 :
bUUUUUUUU ;
0<
bUUUUUUUU =
b0 >
0?
bUUUUUUUU @
0A
0B
b0000000 C
bUUUU D
0E
0F
b1 G
0H
0I
0J
b1 K
0L
#4000000
1!
1(
1E
b10 G
1I
b10 K
#8000000
0!
0(
0E
0I
#12000000
1!
1(
1E
b11 G
1I
b11 K
#16000000
0!
0(
0E
0I
#20000000
1!
1(
1E
b100 G
1I
b100 K
#24000000
0!
0(
0E
0I
#28000000
1!
1(
1E
b101 G
1I
b101 K
#32000000
0!
0(
0E
0I
#36000000
1!
1(
1E
b110 G
1I
b110 K
#40000000
0!
0(
0E
0I
#44000000
1!
1(
1,
1/
b10000 1
b0000UUUU 2
13
b10000 6
b10000 8
19
b10000 :
b0000UUUU ;
1<
b0000UUUU =
b11111010 >
1?
b0000UUUU @
1E
1F
b1 G
1H
1I
b111 K
#48000000
0!
0(
0E
0I
#52000000
1!
1(
1E
b10 G
1I
b1000 K
#56000000
0!
0(
0E
0I
#60000000
1!
1(
1E
b11 G
1I
b1001 K
#64000000
0!
0(
0E
0I
#68000000
1!
1(
1E
b100 G
1I
b1010 K
#72000000
0!
0(
0E
0I
#76000000
1!
1(
1E
b101 G
1I
b1011 K
#80000000
0!
0(
0E
0I
#84000000
1!
1(
1E
b110 G
1I
b1100 K
#88000000
0!
0(
0E
0I
#92000000
1!
b1101 #
1(
b1101 *
0/
03
b1101 5
b1101 7
09
1E
0F
b1 G
0H
1I
b1101 K
#96000000
0!
0(
0E
0I
#100000000
1!
1(
1E
b10 G
1I
b1110 K
#104000000
0!
0(
0E
0I
#108000000
1!
1(
1E
b11 G
1I
b1111 K
#112000000
0!
0(
0E
0I
#116000000
1!
1(
1E
b100 G
1I
b10000 K
#120000000
0!
0(
0E
0I
#124000000
1!
1(
1E
b101 G
1I
b10001 K
#128000000
0!
0(
0E
0I
#132000000
1!
1(
1E
b110 G
1I
b10010 K
#136000000
0!
0(
0E
0I
#140000000
1!
1(
1/
13
19
b11111001 >
1E
1F
b1 G
1H
1I
b10011 K
#144000000
0!
0(
0E
0I
#148000000
1!
1(
1E
b10 G
1I
b10100 K
#152000000
0!
0(
0E
0I
#156000000
1!
1(
1E
b11 G
1I
b10101 K
#160000000
0!
0(
0E
0I
#164000000
1!
1(
1E
b100 G
1I
b10110 K
#168000000
0!
0(
0E
0I
#172000000
1!
1(
1E
b101 G
1I
b10111 K
#176000000
0!
0(
0E
0I
#180000000
1!
1(
1E
b110 G
1I
b11000 K
#184000000
0!
0(
0E
0I
#188000000
1!
b1011 #
1(
b1011 *
0/
03
b1011 5
b1011 7
09
1E
0F
b1 G
0H
1I
b11001 K
#192000000
0!
0(
0E
0I
#196000000
1!
1(
1E
b10 G
1I
b11010 K
#200000000
0!
0(
0E
0I
#204000000
1!
1(
1E
b11 G
1I
b11011 K
#208000000
0!
0(
0E
0I
#212000000
1!
1(
1E
b100 G
1I
b11100 K
#216000000
0!
0(
0E
0I
#220000000
1!
1(
1E
b101 G
1I
b11101 K
#224000000
0!
0(
0E
0I
#228000000
1!
1(
1E
b110 G
1I
b11110 K
#232000000
0!
0(
0E
0I
#236000000
1!
1(
1/
13
19
b11111000 >
1E
1F
b1 G
1H
1I
b11111 K
#240000000
0!
0(
0E
0I
#244000000
1!
1(
1E
b10 G
1I
b100000 K
#248000000
0!
0(
0E
0I
#252000000
1!
1(
1E
b11 G
1I
b100001 K
#256000000
0!
0(
0E
0I
#260000000
1!
1(
1E
b100 G
1I
b100010 K
#264000000
0!
0(
0E
0I
#268000000
1!
1(
1E
b101 G
1I
b100011 K
#272000000
0!
0(
0E
0I
#276000000
1!
1(
1E
b110 G
1I
b100100 K
#280000000
0!
0(
0E
0I
#284000000
1!
b0111 #
1(
b0111 *
0/
03
b0111 5
b0111 7
09
1E
0F
b1 G
0H
1I
b100101 K
#288000000
0!
0(
0E
0I
#292000000
1!
1(
1E
b10 G
1I
b100110 K
#296000000
0!
0(
0E
0I
#300000000
1!
1(
1E
b11 G
1I
b100111 K
#304000000
0!
0(
0E
0I
#308000000
1!
1(
1E
b100 G
1I
b101000 K
#312000000
0!
0(
0E
0I
#316000000
1!
1(
1E
b101 G
1I
b101001 K
#320000000
0!
0(
0E
0I
#324000000
1!
1(
1E
b110 G
1I
b101010 K
#328000000
0!
0(
0E
0I
#332000000
1!
1(
1/
13
19
b11110111 >
1E
1F
b1 G
1H
1I
b101011 K
#336000000
0!
0(
0E
0I
#340000000
1!
1(
1E
b10 G
1I
b101100 K
#344000000
0!
0(
0E
0I
#348000000
1!
1(
1E
b11 G
1I
b101101 K
#352000000
0!
0(
0E
0I
#356000000
1!
1(
1E
b100 G
1I
b101110 K
#360000000
0!
0(
0E
0I
#364000000
1!
1(
1E
b101 G
1I
b101111 K
#368000000
0!
0(
0E
0I
#372000000
1!
1(
1E
b110 G
1I
b110000 K
#376000000
0!
0(
0E
0I
#380000000
1!
b1110 #
1(
b1110 *
0/
03
b1110 5
b1110 7
09
1E
0F
b1 G
0H
1I
b110001 K
#384000000
0!
0(
0E
0I
#388000000
1!
1(
1E
b10 G
1I
b110010 K
#392000000
0!
0(
0E
0I
#396000000
1!
1(
1E
b11 G
1I
b110011 K
#400000000
0!
0(
0E
0I
#404000000
1!
1(
1E
b100 G
1I
b110100 K
#408000000
0!
0(
0E
0I
#412000000
1!
1(
1E
b101 G
1I
b110101 K
#416000000
0!
0(
0E
0I
#420000000
1!
1(
1E
b110 G
1I
b110110 K
#424000000
0!
0(
0E
0I
#428000000
1!
1(
1/
13
19
b11110110 >
1E
1F
b1 G
1H
1I
b110111 K
#432000000
0!
0(
0E
0I
#436000000
1!
1(
1E
b10 G
1I
b111000 K
#440000000
0!
0(
0E
0I
#444000000
1!
1(
1E
b11 G
1I
b111001 K
#448000000
0!
0(
0E
0I
#452000000
1!
1(
1E
b100 G
1I
b111010 K
#456000000
0!
0(
0E
0I
#460000000
1!
1(
1E
b101 G
1I
b111011 K
#464000000
0!
0(
0E
0I
#468000000
1!
1(
1E
b110 G
1I
b111100 K
#472000000
0!
0(
0E
0I
#476000000
1!
b1101 #
1(
b1101 *
0/
03
b1101 5
b1101 7
09
1E
0F
b1 G
0H
1I
b111101 K
#480000000
0!
0(
0E
0I
#484000000
1!
1(
1E
b10 G
1I
b111110 K
#488000000
0!
0(
0E
0I
#492000000
1!
1(
1E
b11 G
1I
b111111 K
#496000000
0!
0(
0E
0I
#500000000
1!
1(
1E
b100 G
1I
b1000000 K
#504000000
0!
0(
0E
0I
#508000000
1!
1(
1E
b101 G
1I
b1000001 K
#512000000
0!
0(
0E
0I
#516000000
1!
1(
1E
b110 G
1I
b1000010 K
#520000000
0!
0(
0E
0I
#524000000
1!
1(
1/
13
19
b11110101 >
1E
1F
b1 G
1H
1I
b1000011 K
#528000000
0!
0(
0E
0I
#532000000
1!
1(
1E
b10 G
1I
b1000100 K
#536000000
0!
0(
0E
0I
#540000000
1!
1(
1E
b11 G
1I
b1000101 K
#544000000
0!
0(
0E
0I
#548000000
1!
1(
1E
b100 G
1I
b1000110 K
#552000000
0!
0(
0E
0I
#556000000
1!
1(
1E
b101 G
1I
b1000111 K
#560000000
0!
0(
0E
0I
#564000000
1!
1(
1E
b110 G
1I
b1001000 K
#568000000
0!
0(
0E
0I
#572000000
1!
b1011 #
1(
b1011 *
0/
03
b1011 5
b1011 7
09
1E
0F
b1 G
0H
1I
b1001001 K
#576000000
0!
0(
0E
0I
#580000000
1!
1(
1E
b10 G
1I
b1001010 K
#584000000
0!
0(
0E
0I
#588000000
1!
1(
1E
b11 G
1I
b1001011 K
#592000000
0!
0(
0E
0I
#596000000
1!
1(
1E
b100 G
1I
b1001100 K
#600000000
0!
0(
0E
0I
#604000000
1!
1(
1E
b101 G
1I
b1001101 K
#608000000
0!
0(
0E
0I
#612000000
1!
1(
1E
b110 G
1I
b1001110 K
#616000000
0!
0(
0E
0I
#620000000
1!
1(
1/
13
19
b11110100 >
1E
1F
b1 G
1H
1I
b1001111 K
#624000000
0!
0(
0E
0I
#628000000
1!
1(
1E
b10 G
1I
b1010000 K
#632000000
0!
0(
0E
0I
#636000000
1!
1(
1E
b11 G
1I
b1010001 K
#640000000
0!
0(
0E
0I
#644000000
1!
1(
1E
b100 G
1I
b1010010 K
#648000000
0!
0(
0E
0I
#652000000
1!
1(
1E
b101 G
1I
b1010011 K
#656000000
0!
0(
0E
0I
#660000000
1!
1(
1E
b110 G
1I
b1010100 K
#664000000
0!
0(
0E
0I
#668000000
1!
b0111 #
1(
b0111 *
0/
03
b0111 5
b0111 7
09
1E
0F
b1 G
0H
1I
b1010101 K
#672000000
0!
0(
0E
0I
#676000000
1!
1(
1E
b10 G
1I
b1010110 K
#680000000
0!
0(
0E
0I
#684000000
1!
1(
1E
b11 G
1I
b1010111 K
#688000000
0!
0(
0E
0I
#692000000
1!
1(
1E
b100 G
1I
b1011000 K
#696000000
0!
0(
0E
0I
#700000000
1!
1(
1E
b101 G
1I
b1011001 K
#704000000
0!
0(
0E
0I
#708000000
1!
1(
1E
b110 G
1I
b1011010 K
#712000000
0!
0(
0E
0I
#716000000
1!
1(
1/
13
19
b11110011 >
1E
1F
b1 G
1H
1I
b1011011 K
#720000000
0!
0(
0E
0I
#724000000
1!
1(
1E
b10 G
1I
b1011100 K
#728000000
0!
0(
0E
0I
#732000000
1!
1(
1E
b11 G
1I
b1011101 K
#736000000
0!
0(
0E
0I
#740000000
1!
1(
1E
b100 G
1I
b1011110 K
#744000000
0!
0(
0E
0I
#748000000
1!
1(
1E
b101 G
1I
b1011111 K
#752000000
0!
0(
0E
0I
#756000000
1!
1(
1E
b110 G
1I
b1100000 K
#760000000
0!
0(
0E
0I
#764000000
1!
b1110 #
1(
b1110 *
0/
03
b1110 5
b1110 7
09
1E
0F
b1 G
0H
1I
b1100001 K
#768000000
0!
0(
0E
0I
#772000000
1!
1(
1E
b10 G
1I
b1100010 K
#776000000
0!
0(
0E
0I
#780000000
1!
1(
1E
b11 G
1I
b1100011 K
#784000000
0!
0(
0E
0I
#788000000
1!
1(
1E
b100 G
1I
b1100100 K
#792000000
0!
0(
0E
0I
#796000000
1!
1(
1E
b101 G
1I
b1100101 K
#800000000
0!
0(
0E
0I
#804000000
1!
1(
1E
b110 G
1I
b1100110 K
#808000000
0!
0(
0E
0I
#812000000
1!
1(
1/
13
19
b11110010 >
1E
1F
b1 G
1H
1I
b1100111 K
#816000000
0!
0(
0E
0I
#820000000
1!
1(
1E
b10 G
1I
b1101000 K
#824000000
0!
0(
0E
0I
#828000000
1!
1(
1E
b11 G
1I
b1101001 K
#832000000
0!
0(
0E
0I
#836000000
1!
1(
1E
b100 G
1I
b1101010 K
#840000000
0!
0(
0E
0I
#844000000
1!
1(
1E
b101 G
1I
b1101011 K
#848000000
0!
0(
0E
0I
#852000000
1!
1(
1E
b110 G
1I
b1101100 K
#856000000
0!
0(
0E
0I
#860000000
1!
b1101 #
1(
b1101 *
0/
03
b1101 5
b1101 7
09
1E
0F
b1 G
0H
1I
b1101101 K
#864000000
0!
0(
0E
0I
#868000000
1!
1(
1E
b10 G
1I
b1101110 K
#872000000
0!
0(
0E
0I
#876000000
1!
1(
1E
b11 G
1I
b1101111 K
#880000000
0!
0(
0E
0I
#884000000
1!
1(
1E
b100 G
1I
b1110000 K
#888000000
0!
0(
0E
0I
#892000000
1!
1(
1E
b101 G
1I
b1110001 K
#896000000
0!
0(
0E
0I
#900000000
1!
1(
1E
b110 G
1I
b1110010 K
#904000000
0!
0(
0E
0I
#908000000
1!
1(
1/
13
19
b11110001 >
1E
1F
b1 G
1H
1I
b1110011 K
#912000000
0!
0(
0E
0I
#916000000
1!
1(
1E
b10 G
1I
b1110100 K
#920000000
0!
0(
0E
0I
#924000000
1!
1(
1E
b11 G
1I
b1110101 K
#928000000
0!
0(
0E
0I
#932000000
1!
1(
1E
b100 G
1I
b1110110 K
#936000000
0!
0(
0E
0I
#940000000
1!
1(
1E
b101 G
1I
b1110111 K
#944000000
0!
0(
0E
0I
#948000000
1!
1(
1E
b110 G
1I
b1111000 K
#952000000
0!
0(
0E
0I
#956000000
1!
b1011 #
1(
b1011 *
0/
03
b1011 5
b1011 7
09
1E
0F
b1 G
0H
1I
b1111001 K
#960000000
0!
0(
0E
0I
#964000000
1!
1(
1E
b10 G
1I
b1111010 K
#968000000
0!
0(
0E
0I
#972000000
1!
1(
1E
b11 G
1I
b1111011 K
#976000000
0!
0(
0E
0I
#980000000
1!
1(
1E
b100 G
1I
b1111100 K
#984000000
0!
0(
0E
0I
#988000000
1!
1(
1E
b101 G
1I
b1111101 K
#992000000
0!
0(
0E
0I
#996000000
1!
1$
b1111110 '
1(
1+
b1111110 .
10
1A
1B
b1111110 C
b0000 D
1E
b110 G
1I
1J
b1 K
1L
#1000000000
0!
0(
0E
0I
#1004000000
1!
1(
1/
13
19
b11110000 >
1E
1F
b1 G
1H
1I
b10 K
#1008000000
0!
0(
0E
0I
#1012000000
1!
1(
1E
b10 G
1I
b11 K
#1016000000
0!
0(
0E
0I
#1020000000
1!
1(
1E
b11 G
1I
b100 K
#1024000000
0!
0(
0E
0I
#1028000000
1!
1(
1E
b100 G
1I
b101 K
#1032000000
0!
0(
0E
0I
#1036000000
1!
1(
1E
b101 G
1I
b110 K
#1040000000
0!
0(
0E
0I
#1044000000
1!
1(
1E
b110 G
1I
b111 K
#1048000000
0!
0(
0E
0I
#1052000000
1!
b0111 #
1(
b0111 *
0/
03
b0111 5
b0111 7
09
1E
0F
b1 G
0H
1I
b1000 K
#1056000000
0!
0(
0E
0I
#1060000000
1!
1(
1E
b10 G
1I
b1001 K
#1064000000
0!
0(
0E
0I
