bidirectional_counter/bidirectional_counter.vhdl
----------------------------------------------------------------------------------
-- Filename : bidirectional_counter.vhdl
-- Author : Antonio Alejandro Andara Lara
-- Date : 28-Oct-10-2022
-- Design Name: bidirectional_counter
-- Module Name: sequential circuits
-- Project Name: VHDL_essentials
-- Description : Implementation of a bidirectional counter using a clock divider
-- Additional Comments:
-- Copyright : University of Alberta, 2022
-- License : CC0 1.0 Universal
----------------------------------------------------------------------------------

LIBRARY IEEE;
USE IEEE.STD_LOGIC_1164.ALL;
USE IEEE.NUMERIC_STD.ALL;

ENTITY bidirectional_counter IS
    PORT (
        direction : IN STD_LOGIC := '1';
        reset     : IN STD_LOGIC := '0';
        clock     : IN STD_LOGIC;
        clock_out : OUT STD_LOGIC;
        count     : OUT STD_LOGIC_VECTOR(3 DOWNTO 0) := "0000"
    );
END ENTITY bidirectional_counter;

ARCHITECTURE Behavioral OF bidirectional_counter IS

    SIGNAL n       : STD_LOGIC_VECTOR(3 DOWNTO 0) := "0000";
    SIGNAL clk_out : STD_LOGIC                    := '0';
    SIGNAL counter : INTEGER                      := 0;

BEGIN
    -- direct assignment
    count     <= n;
    clock_out <= clk_out;

    -- here we will define our clock divider
    clock_divider : PROCESS (clock)
    BEGIN
        IF rising_edge(clock) THEN
            -- IMPORTANT: FOR IMPLEMENTATION ON THE BOARD CHANGE THE VALUE 2 TO 62500000
            -- This is because the inner FPGA clock we're using is 125 MHz.
            -- So counting 62500000 cycles will give us a 1Hz output signal
            IF counter < 2 THEN
                counter <= counter + 1;
            ELSE
                counter <= 0;
                clk_out <= NOT clk_out;
            END IF;
        END IF;
    END PROCESS;

    -- this process will be triggered by the clock divider output
    PROCESS (clk_out)
    BEGIN
        IF rising_edge(clk_out) THEN
            -- first we check the direction of the counter
            -- and then we make the appropriate decision
            -- about what the next value should be
            -- depending on the current value of the counter
            -- and the state of the reset input
            IF direction = '1' THEN
                IF n = "1111" OR reset = '1' THEN
                    n <= "0000";
                ELSE
                    n <= STD_LOGIC_VECTOR(unsigned(n) + 1);
                END IF;
            ELSE
                IF n = "0000" OR reset = '1' THEN
                    n <= "1111";
                ELSE
                    n <= STD_LOGIC_VECTOR(unsigned(n) - 1);
                END IF;
            END IF;

        END IF;
    END PROCESS;
END ARCHITECTURE Behavioral;

bidirectional_counter/bidirectional_counter_tb.vhdl
----------------------------------------------------------------------------------
-- Filename : bidirectional_counter_tb.vhdl
-- Author : Antonio Alejandro Andara Lara
-- Date : 28-Oct-10-2022
-- Design Name: bidirectional_counter
-- Module Name: sequential circuits
-- Project Name: VHDL_essentials
-- Description : Implementation of a testbench for a bidirectional counter
-- Additional Comments:
-- Copyright : University of Alberta, 2022
-- License : CC0 1.0 Universal
----------------------------------------------------------------------------------

LIBRARY IEEE;
USE IEEE.STD_LOGIC_1164.ALL;
USE IEEE.NUMERIC_STD.ALL;

ENTITY bidirectional_counter_tb IS
    -- Empty
END bidirectional_counter_tb;

ARCHITECTURE Behavioral OF bidirectional_counter_tb IS

    SIGNAL direction, reset, clock, clock_out : STD_LOGIC := '1';
    SIGNAL count                   : STD_LOGIC_VECTOR(3 DOWNTO 0);

    -- Using Component instantiation for the counter
    COMPONENT bidirectional_counter
        PORT (
            direction : IN STD_LOGIC := '1';
            reset     : IN STD_LOGIC := '0';
            clock     : IN STD_LOGIC:='0';
            clock_out : OUT STD_LOGIC:='0';
            count     : OUT STD_LOGIC_VECTOR(3 DOWNTO 0)
        );
    END COMPONENT;

BEGIN
    -- creating the component instance
    DUT : bidirectional_counter PORT MAP(direction => direction, reset => reset, clock => clock, clock_out=>clock_out, count => count);

    -- this process will create a clock with an 8 ns period
    clock_process : PROCESS (clock)
    BEGIN
        clock <= NOT clock AFTER 4 ns;
    END PROCESS;

    -- here we manipulate the inputs in order to verify the behavior of our simulated circuit
    Stimulus : PROCESS IS BEGIN
        WAIT FOR 40 ns;
        direction <= '0';
        WAIT FOR 40 ns;
        reset <= '0';
        WAIT FOR 120 ns;
        direction <= '1';
        WAIT FOR 120 ns;
        WAIT;
    END PROCESS;

END Behavioral;

bidirectional_counter/bidirectional_counter.vcd
$date
  Thu Nov  3 14:47:05 2022
$end
$version
  GHDL v0
$end
$timescale
  1 fs
$end
$scope module standard $end
$upscope $end
$scope module std_logic_1164 $end
$upscope $end
$scope module numeric_std $end
$upscope $end
$scope module bidirectional_counter_tb $end
$var reg 1 ! direction $end
$var reg 1 " reset $end
$var reg 1 # clock $end
$var reg 1 $ clock_out $end
$var reg 4 % count[3:0] $end
$scope module dut $end
$var reg 1 & direction $end
$var reg 1 ' reset $end
$var reg 1 ( clock $end
$var reg 1 ) clock_out $end
$var reg 4 * count[3:0] $end
$var reg 4 + n[3:0] $end
$var reg 1 , clk_out $end
$var integer 32 - counter $end
$upscope $end
$upscope $end
$enddefinitions $end
#0
1!
1"
1#
0$
b0000 %
1&
1'
1(
0)
b0000 *
b0000 +
0,
b0 -
#4000000
0#
0(
#8000000
1#
1(
b1 -
#12000000
0#
0(
#16000000
1#
1(
b10 -
#20000000
0#
0(
#24000000
1#
1$
1(
1)
1,
b0 -
#28000000
0#
0(
#32000000
1#
1(
b1 -
#36000000
0#
0(
#40000000
0!
1#
0&
1(
b10 -
#44000000
0#
0(
#48000000
1#
0$
1(
0)
0,
b0 -
#52000000
0#
0(
#56000000
1#
1(
b1 -
#60000000
0#
0(
#64000000
1#
1(
b10 -
#68000000
0#
0(
#72000000
1#
1$
b1111 %
1(
1)
b1111 *
b1111 +
1,
b0 -
#76000000
0#
0(
#80000000
0"
1#
0'
1(
b1 -
#84000000
0#
0(
#88000000
1#
1(
b10 -
#92000000
0#
0(
#96000000
1#
0$
1(
0)
0,
b0 -
#100000000
0#
0(
#104000000
1#
1(
b1 -
#108000000
0#
0(
#112000000
1#
1(
b10 -
#116000000
0#
0(
#120000000
1#
1$
b1110 %
1(
1)
b1110 *
b1110 +
1,
b0 -
#124000000
0#
0(
#128000000
1#
1(
b1 -
#132000000
0#
0(
#136000000
1#
1(
b10 -
#140000000
0#
0(
#144000000
1#
0$
1(
0)
0,
b0 -
#148000000
0#
0(
#152000000
1#
1(
b1 -
#156000000
0#
0(
#160000000
1#
1(
b10 -
#164000000
0#
0(
#168000000
1#
1$
b1101 %
1(
1)
b1101 *
b1101 +
1,
b0 -
#172000000
0#
0(
#176000000
1#
1(
b1 -
#180000000
0#
0(
#184000000
1#
1(
b10 -
#188000000
0#
0(
#192000000
1#
0$
1(
0)
0,
b0 -
#196000000
0#
0(
#200000000
1!
1#
1&
1(
b1 -
#204000000
0#
0(
#208000000
1#
1(
b10 -
#212000000
0#
0(
#216000000
1#
1$
b1110 %
1(
1)
b1110 *
b1110 +
1,
b0 -
#220000000
0#
0(
#224000000
1#
1(
b1 -
#228000000
0#
0(
#232000000
1#
1(
b10 -
#236000000
0#
0(
#240000000
1#
0$
1(
0)
0,
b0 -
#244000000
0#
0(
#248000000
1#
1(
b1 -
#252000000
0#
0(
#256000000
1#
1(
b10 -
#260000000
0#
0(
#264000000
1#
1$
b1111 %
1(
1)
b1111 *
b1111 +
1,
b0 -
#268000000
0#
0(
#272000000
1#
1(
b1 -
#276000000
0#
0(
#280000000
1#
1(
b10 -
#284000000
0#
0(
#288000000
1#
0$
1(
0)
0,
b0 -
#292000000
0#
0(
#296000000
1#
1(
b1 -
#300000000
0#
0(
#304000000
1#
1(
b10 -
#308000000
0#
0(
#312000000
1#
1$
b0000 %
1(
1)
b0000 *
b0000 +
1,
b0 -
#316000000
0#
0(
#320000000
1#
1(
b1 -
#324000000
0#
0(
#328000000
1#
1(
b10 -
#332000000
0#
0(
#336000000
1#
0$
1(
0)
0,
b0 -
#340000000
0#
0(
#344000000
1#
1(
b1 -
#348000000
0#
0(
#352000000
1#
1(
b10 -
#356000000
0#
0(
#360000000
1#
1$
b0001 %
1(
1)
b0001 *
b0001 +
1,
b0 -
#364000000
0#
0(
#368000000
1#
1(
b1 -
#372000000
0#
0(
#376000000
1#
1(
b10 -
#380000000
0#
0(
#384000000
1#
0$
1(
0)
0,
b0 -
#388000000
0#
0(
#392000000
1#
1(
b1 -
#396000000
0#
0(
#400000000
1#
1(
b10 -
#404000000
0#
0(
#408000000
1#
1$
b0010 %
1(
1)
b0010 *
b0010 +
1,
b0 -
#412000000
0#
0(
#416000000
1#
1(
b1 -
#420000000
0#
0(
#424000000
1#
1(
b10 -
#428000000
0#
0(
#432000000
1#
0$
1(
0)
0,
b0 -
#436000000
0#
0(
#440000000
1#
1(
b1 -
#444000000
0#
0(
#448000000
1#
1(
b10 -
#452000000
0#
0(
#456000000
1#
1$
b0011 %
1(
1)
b0011 *
b0011 +
1,
b0 -
#460000000
0#
0(
#464000000
1#
1(
b1 -
#468000000
0#
0(
#472000000
1#
1(
b10 -
#476000000
0#
0(
#480000000
1#
0$
1(
0)
0,
b0 -
#484000000
0#
0(
#488000000
1#
1(
b1 -
#492000000
0#
0(
#496000000
1#
1(
b10 -
